freetar/backend.py
freetar/static/custom.js
freetar/static/guitar.png
freetar/templates/about.html
freetar/templates/base.html
freetar/templates/error.html
freetar/templates/index.html
freetar/templates/macros.j2
freetar/templates/tab.html
freetar/ug.py
freetar/utils.py
freetar-0.16.0.dist-info/METADATA
freetar-0.16.0.dist-info/WHEEL
freetar-0.16.0.dist-info/entry_points.txt
freetar-0.16.0.dist-info/licenses/LICENSE
freetar-0.16.0.dist-info/RECORD
