Metadata-Version: 2.4
Name: freetar
Version: 0.16.0
Summary: 
License-File: LICENSE
Author: kmille
Author-email: github@androidloves.me
Requires-Python: >=3.9,<4.0
Classifier: Programming Language :: Python :: 3
Classifier: Programming Language :: Python :: 3.9
Classifier: Programming Language :: Python :: 3.10
Classifier: Programming Language :: Python :: 3.11
Classifier: Programming Language :: Python :: 3.12
Classifier: Programming Language :: Python :: 3.13
Classifier: Programming Language :: Python :: 3.14
Requires-Dist: beautifulsoup4 (>=4.12.0,<5.0.0)
Requires-Dist: flask (>=3.0.30,<4.0.0)
Requires-Dist: flask-caching (>=2.3.1,<3.0.0)
Requires-Dist: flask-minify (>=0.50,<0.51)
Requires-Dist: requests[socks] (>=2.32.3,<3.0.0)
Requires-Dist: waitress (>=3.0.2,<4.0.0)
Project-URL: Homepage, https://github.com/kmille/freetar
Project-URL: Repository, https://github.com/kmille/freetar
